py_sse_client-1.0.1.dist-info/licenses/LICENSE
pysse/__init__.py
pysse/client.py
pysse/event.py
pysse/exceptions.py
py_sse_client-1.0.1.dist-info/METADATA
py_sse_client-1.0.1.dist-info/WHEEL
py_sse_client-1.0.1.dist-info/top_level.txt
py_sse_client-1.0.1.dist-info/RECORD
